[
  {
    "month":3,
    "demo_age_5_17":975297,
    "demo_age_17_":10169053,
    "adult_ratio":0.9124850709
  },
  {
    "month":4,
    "demo_age_5_17":198588,
    "demo_age_17_":1315962,
    "adult_ratio":0.8688798653
  },
  {
    "month":5,
    "demo_age_5_17":204893,
    "demo_age_17_":1361394,
    "adult_ratio":0.8691855324
  },
  {
    "month":6,
    "demo_age_5_17":197767,
    "demo_age_17_":1487795,
    "adult_ratio":0.8826699937
  },
  {
    "month":7,
    "demo_age_5_17":288449,
    "demo_age_17_":1932266,
    "adult_ratio":0.870109852
  },
  {
    "month":9,
    "demo_age_5_17":770340,
    "demo_age_17_":6551801,
    "adult_ratio":0.8947930667
  },
  {
    "month":10,
    "demo_age_5_17":478940,
    "demo_age_17_":4530829,
    "adult_ratio":0.9043987857
  },
  {
    "month":11,
    "demo_age_5_17":820786,
    "demo_age_17_":8564652,
    "adult_ratio":0.9125468625
  },
  {
    "month":12,
    "demo_age_5_17":925509,
    "demo_age_17_":8507900,
    "adult_ratio":0.9018902923
  }
]